geotopy/__init__.py
geotopy/__main__.py
geotopy/keywords.json
geotopy-0.5.dist-info/LICENSE
geotopy-0.5.dist-info/METADATA
geotopy-0.5.dist-info/WHEEL
geotopy-0.5.dist-info/top_level.txt
geotopy-0.5.dist-info/RECORD
